amt/__init__.py
amt/amt.py
amt/cli.py
amt/canonical/__init__.py
amt/canonical/canonical.py
amt/canonical/command.py
amt/file_io/__init__.py
amt/file_io/file_io.py
amt/load/__init__.py
amt/load/command.py
amt/load/load.py
amt/meta/__init__.py
amt/meta/meta.py
amt/render/__init__.py
amt/render/command.py
amt/render/render.py
amt/save/__init__.py
amt/save/save.py
amt/uid/__init__.py
amt/uid/command.py
amt/uid/uid.py
amtool-0.1.9.dist-info/AUTHORS.rst
amtool-0.1.9.dist-info/LICENSE
amtool-0.1.9.dist-info/METADATA
amtool-0.1.9.dist-info/WHEEL
amtool-0.1.9.dist-info/entry_points.txt
amtool-0.1.9.dist-info/top_level.txt
amtool-0.1.9.dist-info/RECORD
