Metadata-Version: 2.1
Name: amtool
Version: 0.1.9
Summary: The Artifacts Management Tool is meant to be a generic means of storing and manipulating artifact data in a human readable text format ideal for colaborative work.
Home-page: https://github.com/bellockk/amtool
Author: Kenneth E. Bellock
Author-email: ken@bellock.net
License: MIT license
Keywords: amtool
Platform: UNKNOWN
Classifier: Development Status :: 2 - Pre-Alpha
Classifier: Intended Audience :: Developers
Classifier: License :: OSI Approved :: MIT License
Classifier: Natural Language :: English
Classifier: Programming Language :: Python :: 3.6
Classifier: Programming Language :: Python :: 3.7
Requires-Dist: Click (>=6.0)
Requires-Dist: click-log (>=0.3.2)
Requires-Dist: click-plugins (>=1.1.1)
Requires-Dist: mako (>=1.0.12)
Requires-Dist: PyYAML (>=5.1)
